rocketreach/__init__.py
rocketreach/account.py
rocketreach/account_gateway.py
rocketreach/exceptions.py
rocketreach/gateway.py
rocketreach/person.py
rocketreach/person_gateway.py
rocketreach/person_search.py
rocketreach/resource.py
rocketreach/result.py
rocketreach/version.py
rocketreach-2.1.7.dist-info/LICENSE.txt
rocketreach-2.1.7.dist-info/METADATA
rocketreach-2.1.7.dist-info/WHEEL
rocketreach-2.1.7.dist-info/top_level.txt
rocketreach-2.1.7.dist-info/RECORD
