Metadata-Version: 2.1
Name: rocketreach
Version: 2.1.7
Summary: Python bindings for RocketReach API
Home-page: https://rocketreach.co
Author: RocketReach
Author-email: engineering@rocketreach.co
Project-URL: Documentation, https://rocketreach.co/api
Project-URL: Source Code, https://github.com/rocketreach/rocketreach_python
Requires-Python: >=3.4
License-File: LICENSE.txt
Requires-Dist: requests >=2.2
